azure/__init__.py
azure/cli/__init__.py
azure/cli/command_modules/__init__.py
azure/cli/command_modules/cdn/__init__.py
azure/cli/command_modules/cdn/_client_factory.py
azure/cli/command_modules/cdn/_help.py
azure/cli/command_modules/cdn/_params.py
azure/cli/command_modules/cdn/_validators.py
azure/cli/command_modules/cdn/commands.py
azure/cli/command_modules/cdn/custom.py
opal_azure_cli_cdn-0.2.6.dist-info/METADATA
opal_azure_cli_cdn-0.2.6.dist-info/WHEEL
opal_azure_cli_cdn-0.2.6.dist-info/top_level.txt
opal_azure_cli_cdn-0.2.6.dist-info/RECORD
